lap/__init__.py
lap/_lapjv.cp39-win_arm64.pyd
lap/lapmod.py
lap/tests/__init__.py
lap/tests/cost_eps.csv.gz
lap/tests/test_arr_loop.py
lap/tests/test_lapjv.py
lap/tests/test_lapmod.py
lap/tests/test_simple.py
lap/tests/test_utils.py
lap-0.5.12.dist-info/LICENSE
lap-0.5.12.dist-info/METADATA
lap-0.5.12.dist-info/WHEEL
lap-0.5.12.dist-info/top_level.txt
lap-0.5.12.dist-info/RECORD
